MANIFEST.in
README.rst
setup.py
ma/__init__.py
ma/constants.py
ma/exceptions.py
ma/progress.py
ma/utility.py
ma/api/__init__.py
ma/api/attribute.py
ma/api/attribute_set.py
ma/api/base_class.py
ma/api/category.py
ma/api/customer.py
ma/api/help.py
ma/api/magento_info.py
ma/api/media.py
ma/api/order.py
ma/api/product.py
ma/api/stock.py
ma/api/store.py
ma/api/custom/__init__.py
ma/api/custom/maintenance.py
ma/api/plugins/__init__.py
ma/api/plugins/netzkollektiv/__init__.py
ma/api/plugins/netzkollektiv/configurable.py
ma/config/__init__.py
ma/config/general.py
ma/config/log.py
ma/config/magento.py
ma/config/maintenance.py
ma/entities/__init__.py
ma/entities/category.py
ma/entities/product.py
ma/resources/README.rst
ma/resources/requirements.txt
ma/resources/scripts/ma_help
ma/resources/scripts/ma_truncate_products
magento_adapter.egg-info/PKG-INFO
magento_adapter.egg-info/SOURCES.txt
magento_adapter.egg-info/dependency_links.txt
magento_adapter.egg-info/not-zip-safe
magento_adapter.egg-info/requires.txt
magento_adapter.egg-info/top_level.txt