Metadata-Version: 1.0
Name: magento-adapter
Version: 0.2.1
Summary: Magento API interfaces
Home-page: https://github.com/CoffeeForThinkers/MagentoAPI
Author: Dustin Oprea
Author-email: dustin@randomingenuity.com
License: GPL3
Platform: UNKNOWN
